cvprac/__init__.py
cvprac/cvp_api.py
cvprac/cvp_client.py
cvprac/cvp_client_errors.py
cvprac-1.4.2.dist-info/LICENSE
cvprac-1.4.2.dist-info/METADATA
cvprac-1.4.2.dist-info/WHEEL
cvprac-1.4.2.dist-info/top_level.txt
cvprac-1.4.2.dist-info/RECORD
