Metadata-Version: 2.1
Name: cvprac
Version: 1.4.2
Summary: Arista Cloudvision(R) Portal Rest API Client written in python
Home-page: https://github.com/aristanetworks/cvprac
Author: Arista Networks, Inc.
Author-email: eosplus-dev@arista.com
License: BSD-3
Download-URL: https://github.com/aristanetworks/cvprac/tarball/1.4.2
Keywords: networking CloudVision development rest api
Platform: UNKNOWN
Classifier: Development Status :: 4 - Beta
Classifier: Intended Audience :: Developers
Classifier: Intended Audience :: System Administrators
Classifier: Topic :: Software Development :: Libraries
Classifier: Topic :: Software Development :: Libraries :: Python Modules
Classifier: Topic :: System :: Networking
Classifier: License :: OSI Approved :: BSD License
Classifier: Programming Language :: Python :: 3 :: Only
Classifier: Programming Language :: Python :: 3.7
Classifier: Programming Language :: Python :: 3.8
Classifier: Programming Language :: Python :: 3.9
Classifier: Programming Language :: Python :: 3.10
Classifier: Programming Language :: Python :: 3.11
Classifier: Programming Language :: Python :: 3.12
License-File: LICENSE
Requires-Dist: requests[socks] (>=2.27.0)
Requires-Dist: packaging (>=23.2)
Provides-Extra: dev
Requires-Dist: check-manifest ; extra == 'dev'
Requires-Dist: pep8 ; extra == 'dev'
Requires-Dist: pyflakes ; extra == 'dev'
Requires-Dist: pylint ; extra == 'dev'
Requires-Dist: coverage ; extra == 'dev'
Requires-Dist: pyyaml ; extra == 'dev'
